evo/aio/__init__.py
evo/aio/_helpers.py
evo/aio/py.typed
evo/aio/transport.py
evo/common/__init__.py
evo/common/_types.py
evo/common/connector.py
evo/common/context.py
evo/common/data.py
evo/common/exceptions.py
evo/common/interfaces.py
evo/common/py.typed
evo/common/service.py
evo/common/io/__init__.py
evo/common/io/bytes.py
evo/common/io/chunked_io_manager.py
evo/common/io/download.py
evo/common/io/exceptions.py
evo/common/io/http.py
evo/common/io/interfaces.py
evo/common/io/storage.py
evo/common/io/upload.py
evo/common/test_tools/__init__.py
evo/common/test_tools/consts.py
evo/common/test_tools/http.py
evo/common/test_tools/io.py
evo/common/test_tools/storage.py
evo/common/test_tools/utils.py
evo/common/utils/__init__.py
evo/common/utils/cache.py
evo/common/utils/data.py
evo/common/utils/feedback.py
evo/common/utils/health_check.py
evo/common/utils/retry.py
evo/common/utils/version.py
evo/discovery/__init__.py
evo/discovery/client.py
evo/discovery/data.py
evo/discovery/py.typed
evo/jmespath/__init__.py
evo/jmespath/py.typed
evo/logging/__init__.py
evo/logging/logging.py
evo/logging/py.typed
evo/notebooks/__init__.py
evo/notebooks/_consts.py
evo/notebooks/_helpers.py
evo/notebooks/authorizer.py
evo/notebooks/env.py
evo/notebooks/py.typed
evo/notebooks/widgets.py
evo/notebooks/assets/EvoBadgeCharcoal_FV.png
evo/notebooks/assets/__init__.py
evo/notebooks/assets/loading.gif
evo/oauth/__init__.py
evo/oauth/authorizer.py
evo/oauth/connector.py
evo/oauth/data.py
evo/oauth/exceptions.py
evo/oauth/oauth_redirect_handler.py
evo/oauth/py.typed
evo/service_manager/__init__.py
evo/service_manager/manager.py
evo/service_manager/py.typed
evo/workspaces/__init__.py
evo/workspaces/_model_config.py
evo/workspaces/client.py
evo/workspaces/data.py
evo/workspaces/exceptions.py
evo/workspaces/parse.py
evo/workspaces/py.typed
evo/workspaces/endpoints/__init__.py
evo/workspaces/endpoints/models.py
evo/workspaces/endpoints/api/__init__.py
evo/workspaces/endpoints/api/admin_api.py
evo_sdk_common-0.5.15.dist-info/METADATA
evo_sdk_common-0.5.15.dist-info/WHEEL
evo_sdk_common-0.5.15.dist-info/licenses/LICENSE.md
evo_sdk_common-0.5.15.dist-info/RECORD
