Metadata-Version: 2.4
Name: evo-sdk-common
Version: 0.5.15
Summary: Python package that establishes a common framework for use by client libraries that interact with Seequent Evo APIs
Project-URL: Source, https://github.com/SeequentEvo/evo-python-sdk
Project-URL: Tracker, https://github.com/SeequentEvo/evo-python-sdk/issues
Project-URL: Homepage, https://www.seequent.com/
Project-URL: Documentation, https://developer.seequent.com/
Author-email: Seequent <support@seequent.com>
License-File: LICENSE.md
Requires-Python: >=3.10
Requires-Dist: pure-interface>=8.0.0
Requires-Dist: pydantic>=2
Requires-Dist: python-dateutil
Provides-Extra: aiohttp
Requires-Dist: aiohttp; extra == 'aiohttp'
Provides-Extra: jmespath
Requires-Dist: jmespath>=1.0.1; extra == 'jmespath'
Provides-Extra: notebooks
Requires-Dist: aiohttp; extra == 'notebooks'
Requires-Dist: ipykernel; extra == 'notebooks'
Requires-Dist: ipython; extra == 'notebooks'
Requires-Dist: ipywidgets; extra == 'notebooks'
Requires-Dist: python-dotenv; extra == 'notebooks'
